Workbook

Sheet COQ
B2: COQ Matrix
B4: Month | C4: Production Quality Cost ($) | D4: Production Value ($) | E4: Production COQ % | F4: Customer Complaint Cost ($) | G4: Sales Revenue ($) | H4: Customer Complaint COQ % | I4: Total Cost of Poor Quality %
B5: 202601 | C5: =Production!J3 -> 25435.17 | D5: =Production!C3 -> 3887918 | E5: =C5/D5 -> 0.0065421056 | F5: =Customer_Complaint!K3 -> 26720 | G5: 10259998 | H5: =F5/G5 -> 0.002604289 | I5: =(C5+F5)/(D5+G5) -> 0.0036864207
B6: 202602 | C6: =Production!J4 -> 20991.75 | D6: =Production!C4 -> 2844879 | E6: =C6/D6 -> 0.0073787848 | F6: =Customer_Complaint!K4 -> 2800 | G6: 11506662 | H6: =F6/G6 -> 0.00024333729 | I6: =(C6+F6)/(D6+G6) -> 0.0016577836
B7: 202603
B8: 202604
B9: 202605
B10: 202606
B11: 202607
B12: 202608
B13: 202609
B14: 202610
B15: 202611
B16: 202612

Sheet Production
B2: Month | C2: Total Production (lbs) | D2: Scrap Produced (lbs) | E2: Offspec Produced (lbs) | F2: Scrap Loss ($/lb) | G2: Offspec Loss ($/lb) | H2: Scrap Loss ($) | I2: Offspec Loss ($) | J2: Production Quality Cost ($)
B3: 202601 | C3: 3887918 | D3: 41697 | F3: 0.61 | G3: 0.338 | H3: =D3*F3 -> 25435.17 | I3: =E3*G3 -> 0 | J3: =H3+I3 -> 25435.17
B4: 202602 | C4: 2844879 | D4: 27625 | E4: 12250 | F4: 0.61 | G4: 0.338 | H4: =D4*F4 -> 16851.25 | I4: =E4*G4 -> 4140.5 | J4: =H4+I4 -> 20991.75
B5: 202603
B6: 202604
B7: 202605
B8: 202606
B9: 202607
B10: 202608
B11: 202609
B12: 202610
B13: 202611

Sheet Customer_Complaint
B2: Month | C2: No. of Complaints | D2: Returned Product (lbs) | E2: Outbound Freight ($) | F2: Return Freight ($) | G2: Warehousing / Handling ($) | H2: Lab / Investigation ($) | I2: Customer Credit / Penalty ($) | J2: Rework Cost ($) | K2: Total Customer Complaint Cost ($)
B3: 202601 | C3: 2 | D3: 42000 | E3: 2500 | F3: 2350 | G3: =D3*0.02 -> 840 | H3: 750 | I3: 6000 | J3: =D3*0.34 -> 14280 | K3: =SUM(E3:J3) -> 26720
B4: 202602 | C4: 1 | D4: 0 | E4: 0 | F4: 0 | G4: =D4*0.02 -> 0 | H4: 800 | I4: 2000 | J4: =D4*0.34 -> 0 | K4: =SUM(E4:J4) -> 2800
B5: 202603
B6: 202604
B7: 202605
B8: 202606
B9: 202607
B10: 202608
B11: 202609
B12: 202610
B13: 202611
B14: 202612

Sheet Production Cost
A2: MONTH | B2: 202601 | C2: 202602 | D2: 202603 | E2: 202604 | F2: 202605 | G2: 202606 | H2: 202607 | I2: 202608 | J2: 202609 | K2: 202610 | L2: 202611 | M2: 202612
A3: BD Price $/LB | B3: 0.294 | C3: 0.373 | D3: 0.412 | E3: 0.51 | F3: 0.51 | G3: 0.5 | H3: 0.48 | I3: 0.46 | J3: 0.43 | K3: 0.41 | L3: 0.39 | M3: 0.39
A4: Styerene Price $/LB | B4: 0.467 | C4: 0.4738 | D4: 0.56219568 | E4: 0.6056149 | F4: 0.62263421 | G4: 0.6007807 | H4: 0.59105895 | I4: 0.58247704 | J4: 0.56820503 | K4: 0.54871059 | L4: 0.52859215 | M4: 0.50345218
A5: Chem, NG, Pipeline Fee Price $/LB | B5: 0.18 | C5: 0.18 | D5: 0.18 | E5: 0.18 | F5: 0.18 | G5: 0.18 | H5: 0.18 | I5: 0.18 | J5: 0.18 | K5: 0.18 | L5: 0.18 | M5: 0.18
A6: Fix Cost Price $/LB | B6: 0.29 | C6: 0.29 | D6: 0.29 | E6: 0.29 | F6: 0.29 | G6: 0.29 | H6: 0.29 | I6: 0.29 | J6: 0.29 | K6: 0.29 | L6: 0.29 | M6: 0.29
A7: Scrap Price Price $/LB | B7: =B3*0.7+B4*0.3-0.14 -> 0.2059 | C7: =C3*0.7+C4*0.3-0.14 -> 0.26324 | D7: =D3*0.7+D4*0.3-0.14 -> 0.31705871 | E7: =E3*0.7+E4*0.3-0.14 -> 0.39868447 | F7: =F3*0.7+F4*0.3-0.14 -> 0.40379026 | G7: =G3*0.7+G4*0.3-0.14 -> 0.39023421 | H7: =H3*0.7+H4*0.3-0.14 -> 0.37331769 | I7: =I3*0.7+I4*0.3-0.14 -> 0.35674311 | ... M7: =M3*0.7+M4*0.3-0.14 -> 0.28403565
A8: Production cost $/LB | B8: =B3*0.7+B4*0.3+B5+B6 -> 0.8159 | C8: =C3*0.7+C4*0.3+C5+C6 -> 0.87324 | D8: =D3*0.7+D4*0.3+D5+D6 -> 0.92705871 | E8: =E3*0.7+E4*0.3+E5+E6 -> 1.0086845 | F8: =F3*0.7+F4*0.3+F5+F6 -> 1.0137903 | G8: =G3*0.7+G4*0.3+G5+G6 -> 1.0002342 | H8: =H3*0.7+H4*0.3+H5+H6 -> 0.98331769 | I8: =I3*0.7+I4*0.3+I5+I6 -> 0.96674311 | ... M8: =M3*0.7+M4*0.3+M5+M6 -> 0.89403565
A9: Loss due to scrap $/LB | B9: =B8-B7 -> 0.61 | C9: =C8-C7 -> 0.61 | D9: =D8-D7 -> 0.61 | E9: =E8-E7 -> 0.61 | F9: =F8-F7 -> 0.61 | G9: =G8-G7 -> 0.61 | H9: =H8-H7 -> 0.61 | I9: =I8-I7 -> 0.61 | ... M9: =M8-M7 -> 0.61
A12: OFFSPEC COST
A13: Lost fixed cost $/LB | B13: =0.29 -> 0.29 | C13: =0.29 -> 0.29 | D13: =0.29 -> 0.29 | E13: =0.29 -> 0.29 | F13: =0.29 -> 0.29 | G13: =0.29 -> 0.29 | H13: =0.29 -> 0.29 | I13: =0.29 -> 0.29 | ... M13: =0.29 -> 0.29
A14: Lost packaging $/LB | B14: 0.03 | C14: 0.03 | D14: 0.03 | E14: 0.03 | F14: 0.03 | G14: 0.03 | H14: 0.03 | I14: 0.03 | J14: 0.03 | K14: 0.03 | L14: 0.03 | M14: 0.03
A15: Additional Labor v | B15: =(30*24)/40000 -> 0.018 | C15: =(30*24)/40000 -> 0.018 | D15: =(30*24)/40000 -> 0.018 | E15: =(30*24)/40000 -> 0.018 | F15: =(30*24)/40000 -> 0.018 | G15: =(30*24)/40000 -> 0.018 | H15: =(30*24)/40000 -> 0.018 | I15: =(30*24)/40000 -> 0.018 | ... M15: =(30*24)/40000 -> 0.018
A16: Loss due to offspec $/LB | B16: =SUM(B13:B15) -> 0.338 | C16: =SUM(C13:C15) -> 0.338 | D16: =SUM(D13:D15) -> 0.338 | E16: =SUM(E13:E15) -> 0.338 | F16: =SUM(F13:F15) -> 0.338 | G16: =SUM(G13:G15) -> 0.338 | H16: =SUM(H13:H15) -> 0.338 | I16: =SUM(I13:I15) -> 0.338 | ... M16: =SUM(M13:M15) -> 0.338

Sheet Definitions
A1: Term | B1: Definition
A2: Production Quality Cost | B2: Internal failure costs incurred before shipment, including scrap and off-spec material losses.
A3: Scrap Produced | B3: Material that cannot be recovered and is permanently lost.
A4: Offspec Produced | B4: Material that does not meet specification but may be downgraded or reworked.
A5: Rework Cost | B5: Incremental labor, energy, and handling cost required to reprocess returned or off-spec material into prime product.
A6: Customer Complaint Cost | B6: All costs incurred due to customer quality issues after shipment, excluding recovered material value.
A7: External Failure Cost | B7: Costs caused by product quality failures after delivery to the customer.
A8: Production COQ % | B8: Production Quality Cost divided by total production value.
A9: Customer Complaint COQ % | B9: Customer Complaint Cost divided by sales revenue.
A10: Total Cost of Poor Quality | B10: Sum of internal and external failure costs expressed as a percentage of sales.
A11: Returned Product Treatment | B11: Returned product is reprocessed and sold as prime; therefore, no material write-off is recorded.
